py_sci_calc/__init__.py
py_sci_calc-0.1.0.dist-info/METADATA
py_sci_calc-0.1.0.dist-info/WHEEL
py_sci_calc-0.1.0.dist-info/entry_points.txt
py_sci_calc-0.1.0.dist-info/RECORD
