Metadata-Version: 2.4
Name: py-sci-calc
Version: 0.1.0
Summary: Add your description here
Author-email: clifton.clark@gmail.com
Requires-Python: >=3.12
Requires-Dist: pint>=0.25.2
Requires-Dist: ptpython>=3.0.32
